{
  "personajes": [
    {
      "vidaMaxima": 100,
      "dialogos": [
        ""
      ],
      "habilidades": [
        {
          "nombre": "Golpe Poderoso",
          "costeMana": 10,
          "danyo": 25,
          "descripcion": "Un ataque fuerte que inflige daño adicional",
          "tipoHabilidad": "ATAQUE"
        },
        {
          "nombre": "Rugido de Batalla",
          "costeMana": 8,
          "danyo": 0,
          "descripcion": "Aumenta la moral del equipo, incrementando el ataque temporalmente",
          "tipoHabilidad": "APOYO"
        }
      ],
      "vida": 100,
      "ataque": 15,
      "velocidad": 10,
      "nombre": "Protagonistas",
      "vivo": true,
      "mana": 50
    }
  ],
  "objetos": [],
  "seed": 86081457,
  "eventos": [
    [
      null,
      null,
      null,
      null,
      {
        "eventoNombre": "trampaEnCamino",
        "completado": false
      },
      {
        "eventoNombre": "generarEnemigoAleatorio",
        "completado": false
      },
      {
        "eventoNombre": "trampaEnCamino",
        "completado": false
      }
    ],
    [
      null,
      null,
      null,
      null,
      {
        "eventoNombre": "encuentroMercader",
        "completado": false
      },
      {
        "eventoNombre": "encuentroMercader",
        "completado": false
      },
      {
        "eventoNombre": "trampaEnCamino",
        "completado": false
      }
    ],
    [
      null,
      null,
      null,
      null,
      null,
      {
        "eventoNombre": "encuentroMercader",
        "completado": false
      },
      {
        "eventoNombre": "ruinasAntiguas",
        "completado": false
      }
    ],
    [
      null,
      null,
      null,
      null,
      null,
      null,
      {
        "eventoNombre": "trampaEnCamino",
        "completado": false
      }
    ],
    [
      null,
      null,
      null,
      null,
      null,
      null,
      null
    ],
    [
      null,
      null,
      null,
      null,
      null,
      null,
      null
    ],
    [
      null,
      null,
      null,
      null,
      null,
      null,
      null
    ]
  ]
}